{
  "pattern": {
    "panels": {
      "back": {
        "translation": [
          -0.17666666666666703,
          9.85,
          -15.51
        ],
        "edges": [
          {
            "endpoints": [
              4,
              3
            ]
          },
          {
            "endpoints": [
              3,
              2
            ]
          },
          {
            "endpoints": [
              2,
              1
            ],
            "curvature": [
              0.3,
              0.4
            ]
          },
          {
            "endpoints": [
              1,
              0
            ]
          },
          {
            "endpoints": [
              0,
              7
            ],
            "curvature": [
              0.5,
              2.7504264517903176
            ]
          },
          {
            "endpoints": [
              7,
              6
            ]
          },
          {
            "endpoints": [
              6,
              5
            ],
            "curvature": [
              0.7,
              0.4
            ]
          },
          {
            "endpoints": [
              5,
              4
            ]
          }
        ],
        "rotation": [
          180.0,
          -0.0,
          180.0
        ],
        "vertices": [
          [
            7.644333472556713,
            19.583333333333332
          ],
          [
            21.050727474741272,
            19.583333333333332
          ],
          [
            24.878132470148774,
            -3.207584387859577
          ],
          [
            20.570056001876633,
            -86.49734389631041
          ],
          [
            -20.570056001876633,
            -86.49734389631041
          ],
          [
            -24.878132470148774,
            -3.207584387859577
          ],
          [
            -21.050727474741272,
            19.583333333333332
          ],
          [
            -7.644333472556713,
            19.583333333333332
          ]
        ]
      },
      "front_right": {
        "translation": [
          0.17666666666666703,
          10.743979826009564,
          18.759999999999998
        ],
        "edges": [
          {
            "endpoints": [
              4,
              5
            ]
          },
          {
            "endpoints": [
              5,
              0
            ]
          },
          {
            "endpoints": [
              0,
              1
            ]
          },
          {
            "endpoints": [
              1,
              2
            ]
          },
          {
            "endpoints": [
              2,
              3
            ],
            "curvature": [
              0.7,
              0.4
            ]
          },
          {
            "endpoints": [
              3,
              4
            ]
          }
        ],
        "rotation": [
          0.0,
          0.0,
          0.0
        ],
        "vertices": [
          [
            0.0,
            4.739589711064463
          ],
          [
            -7.644333472556713,
            18.703703703703702
          ],
          [
            -21.050727474741272,
            18.703703703703702
          ],
          [
            -24.878132470148774,
            -4.087214017489201
          ],
          [
            -20.570056001876633,
            -87.37697352594006
          ],
          [
            0.0,
            -87.37697352594006
          ]
        ]
      },
      "front_left": {
        "translation": [
          0.17666666666666703,
          10.743979826009564,
          18.759999999999998
        ],
        "edges": [
          {
            "endpoints": [
              1,
              2
            ]
          },
          {
            "endpoints": [
              2,
              3
            ]
          },
          {
            "endpoints": [
              3,
              4
            ],
            "curvature": [
              0.3,
              0.4
            ]
          },
          {
            "endpoints": [
              4,
              5
            ]
          },
          {
            "endpoints": [
              5,
              0
            ]
          },
          {
            "endpoints": [
              0,
              1
            ]
          }
        ],
        "rotation": [
          0.0,
          0.0,
          0.0
        ],
        "vertices": [
          [
            0.0,
            4.739589711064463
          ],
          [
            0.0,
            -87.37697352594006
          ],
          [
            20.570056001876633,
            -87.37697352594006
          ],
          [
            24.878132470148774,
            -4.087214017489201
          ],
          [
            21.050727474741272,
            18.703703703703702
          ],
          [
            7.644333472556713,
            18.703703703703702
          ]
        ]
      }
    },
    "stitches": [
      [
        {
          "edge": 3,
          "panel": "back"
        },
        {
          "edge": 3,
          "panel": "front_right"
        }
      ],
      [
        {
          "edge": 1,
          "panel": "back"
        },
        {
          "edge": 5,
          "panel": "front_right"
        }
      ],
      [
        {
          "edge": 7,
          "panel": "back"
        },
        {
          "edge": 1,
          "panel": "front_left"
        }
      ],
      [
        {
          "edge": 5,
          "panel": "back"
        },
        {
          "edge": 3,
          "panel": "front_left"
        }
      ]
    ],
    "panel_order": [
      "front_right",
      "back",
      "front_left"
    ]
  },
  "properties": {
    "curvature_coords": "relative",
    "normalize_panel_translation": false,
    "units_in_meter": 100,
    "normalized_edge_loops": true
  },
  "parameters": {
    "low_wide": {
      "influence": [
        {
          "edge_list": [
            {
              "direction": "both",
              "id": 0
            }
          ],
          "panel": "back"
        },
        {
          "edge_list": [
            {
              "direction": "end",
              "id": 0
            }
          ],
          "panel": "front_left"
        },
        {
          "edge_list": [
            {
              "direction": "start",
              "id": 0
            }
          ],
          "panel": "front_right"
        }
      ],
      "range": [
        0.7,
        2.5
      ],
      "type": "length",
      "value": 0.8268328029267714
    },
    "length": {
      "influence": [
        {
          "edge_list": [
            {
              "direction": "end",
              "id": [
                5,
                0
              ],
              "along": [
                0,
                1
              ]
            }
          ],
          "panel": "front_right"
        },
        {
          "edge_list": [
            {
              "direction": "start",
              "id": [
                0,
                1
              ],
              "along": [
                0,
                1
              ]
            }
          ],
          "panel": "front_left"
        },
        {
          "edge_list": [
            {
              "direction": "start",
              "id": 1,
              "along": [
                0,
                1
              ]
            },
            {
              "direction": "end",
              "id": 7,
              "along": [
                0,
                1
              ]
            }
          ],
          "panel": "back"
        }
      ],
      "range": [
        0.3,
        2.7
      ],
      "type": "length",
      "value": 1.986978012510602
    },
    "collar_wide": {
      "influence": [
        {
          "edge_list": [
            {
              "direction": "end",
              "id": [
                2
              ],
              "along": [
                1,
                0
              ]
            }
          ],
          "panel": "front_right"
        },
        {
          "edge_list": [
            {
              "direction": "start",
              "id": [
                4
              ],
              "along": [
                1,
                0
              ]
            }
          ],
          "panel": "front_left"
        },
        {
          "edge_list": [
            {
              "direction": "both",
              "id": 4
            }
          ],
          "panel": "back"
        }
      ],
      "range": [
        0.5,
        1.5
      ],
      "type": "length",
      "value": 0.7989051048142686
    },
    "bcollar_depth": {
      "influence": [
        {
          "edge_list": [
            4
          ],
          "panel": "back"
        }
      ],
      "range": [
        0.1,
        12
      ],
      "type": "curve",
      "value": 9.168088172634393
    },
    "wideness": {
      "influence": [
        {
          "edge_list": [
            {
              "direction": "end",
              "id": [
                2,
                3,
                4
              ],
              "along": [
                1,
                0
              ]
            },
            {
              "direction": "start",
              "id": 0,
              "along": [
                1,
                0
              ]
            }
          ],
          "panel": "front_right"
        },
        {
          "edge_list": [
            {
              "direction": "start",
              "id": [
                2,
                3,
                4
              ],
              "along": [
                1,
                0
              ]
            },
            {
              "direction": "end",
              "id": 0,
              "along": [
                1,
                0
              ]
            }
          ],
          "panel": "front_left"
        },
        {
          "edge_list": [
            {
              "direction": "both",
              "id": [
                2,
                3,
                4,
                5,
                6
              ]
            },
            {
              "direction": "both",
              "id": 0
            }
          ],
          "panel": "back"
        }
      ],
      "range": [
        0.9,
        1.5
      ],
      "type": "length",
      "value": 1.1482214986222512
    },
    "fcollar_depth": {
      "influence": [
        {
          "edge_list": [
            {
              "direction": "start",
              "along": [
                0,
                1
              ],
              "id": 2
            }
          ],
          "panel": "front_right"
        },
        {
          "edge_list": [
            {
              "direction": "end",
              "along": [
                0,
                1
              ],
              "id": 4
            }
          ],
          "panel": "front_left"
        }
      ],
      "range": [
        0.1,
        3
      ],
      "type": "length",
      "value": 1.1969240565119355
    },
    "sldepth": {
      "influence": [
        {
          "edge_list": [
            {
              "direction": "end",
              "along": [
                0,
                1
              ],
              "id": 4
            }
          ],
          "panel": "front_right"
        },
        {
          "edge_list": [
            {
              "direction": "start",
              "along": [
                0,
                1
              ],
              "id": 2
            }
          ],
          "panel": "front_left"
        },
        {
          "edge_list": [
            {
              "direction": "end",
              "along": [
                0,
                1
              ],
              "id": 6
            },
            {
              "direction": "start",
              "along": [
                0,
                1
              ],
              "id": 2
            }
          ],
          "panel": "back"
        }
      ],
      "range": [
        0.85,
        2.5
      ],
      "type": "length",
      "value": 1.3674550632715747
    }
  },
  "parameter_order": [
    "collar_wide",
    "fcollar_depth",
    "bcollar_depth",
    "wideness",
    "length",
    "low_wide",
    "sldepth"
  ]
}