{
    "pattern": {
        "panels": {
            "back": {
                "translation": [
                    -0.17666666666666703,
                    9.85,
                    -14.176666666666666
                ],
                "edges": [
                    {
                        "endpoints": [
                            4,
                            3
                        ]
                    },
                    {
                        "endpoints": [
                            3,
                            2
                        ]
                    },
                    {
                        "endpoints": [
                            2,
                            1
                        ],
                        "curvature": [
                            0.3,
                            0.4
                        ]
                    },
                    {
                        "endpoints": [
                            1,
                            0
                        ]
                    },
                    {
                        "endpoints": [
                            0,
                            8
                        ]
                    },
                    {
                        "endpoints": [
                            8,
                            7
                        ]
                    },
                    {
                        "endpoints": [
                            7,
                            6
                        ]
                    },
                    {
                        "endpoints": [
                            6,
                            5
                        ],
                        "curvature": [
                            0.7,
                            0.4
                        ]
                    },
                    {
                        "endpoints": [
                            5,
                            4
                        ]
                    }
                ],
                "rotation": [
                    180.0,
                    -0.0,
                    180.0
                ],
                "vertices": [
                    [
                        13.765382523528718,
                        19.583333333333332
                    ],
                    [
                        26.0635509280114,
                        19.583333333333332
                    ],
                    [
                        30.802378369468016,
                        -10.271436501292342
                    ],
                    [
                        52.07771442445236,
                        -69.97028576363543
                    ],
                    [
                        -52.07771442445236,
                        -69.97028576363543
                    ],
                    [
                        -30.802378369468016,
                        -10.271436501292342
                    ],
                    [
                        -26.0635509280114,
                        19.583333333333332
                    ],
                    [
                        -13.765382523528718,
                        19.583333333333332
                    ],
                    [
                        0.0,
                        16.916666666666664
                    ]
                ]
            },
            "front_right": {
                "translation": [
                    -5.176666666666667,
                    10.743979826009564,
                    15.426666666666666
                ],
                "edges": [
                    {
                        "endpoints": [
                            4,
                            5
                        ]
                    },
                    {
                        "endpoints": [
                            5,
                            0
                        ]
                    },
                    {
                        "endpoints": [
                            0,
                            1
                        ]
                    },
                    {
                        "endpoints": [
                            1,
                            2
                        ]
                    },
                    {
                        "endpoints": [
                            2,
                            3
                        ],
                        "curvature": [
                            0.7,
                            0.4
                        ]
                    },
                    {
                        "endpoints": [
                            3,
                            4
                        ]
                    }
                ],
                "rotation": [
                    0.0,
                    0.0,
                    0.0
                ],
                "vertices": [
                    [
                        0.0,
                        17.237016640751783
                    ],
                    [
                        -13.765382523528718,
                        18.703703703703702
                    ],
                    [
                        -26.0635509280114,
                        18.703703703703702
                    ],
                    [
                        -30.802378369468016,
                        -11.151066130921965
                    ],
                    [
                        -52.07771442445236,
                        -70.84991539326506
                    ],
                    [
                        0.0,
                        -70.84991539326506
                    ]
                ]
            },
            "front_left": {
                "translation": [
                    5.176666666666667,
                    10.743979826009564,
                    15.426666666666666
                ],
                "edges": [
                    {
                        "endpoints": [
                            1,
                            2
                        ]
                    },
                    {
                        "endpoints": [
                            2,
                            3
                        ]
                    },
                    {
                        "endpoints": [
                            3,
                            4
                        ],
                        "curvature": [
                            0.3,
                            0.4
                        ]
                    },
                    {
                        "endpoints": [
                            4,
                            5
                        ]
                    },
                    {
                        "endpoints": [
                            5,
                            0
                        ]
                    },
                    {
                        "endpoints": [
                            0,
                            1
                        ]
                    }
                ],
                "rotation": [
                    0.0,
                    0.0,
                    0.0
                ],
                "vertices": [
                    [
                        0.0,
                        17.237016640751783
                    ],
                    [
                        0.0,
                        -70.84991539326506
                    ],
                    [
                        52.07771442445236,
                        -70.84991539326506
                    ],
                    [
                        30.802378369468016,
                        -11.151066130921965
                    ],
                    [
                        26.0635509280114,
                        18.703703703703702
                    ],
                    [
                        13.765382523528718,
                        18.703703703703702
                    ]
                ]
            },
            "Lhood": {
                "translation": [
                    8.666666666666666,
                    53.33333333333333,
                    -6.666666666666666
                ],
                "edges": [
                    {
                        "endpoints": [
                            4,
                            3
                        ]
                    },
                    {
                        "endpoints": [
                            3,
                            2
                        ]
                    },
                    {
                        "endpoints": [
                            2,
                            1
                        ],
                        "curvature": [
                            0.7,
                            -0.6
                        ]
                    },
                    {
                        "endpoints": [
                            1,
                            0
                        ]
                    },
                    {
                        "endpoints": [
                            0,
                            4
                        ]
                    }
                ],
                "rotation": [
                    0.0,
                    90.0,
                    0.0
                ],
                "vertices": [
                    [
                        -23.333333333333332,
                        24.756423684317213
                    ],
                    [
                        -5.688060483173091,
                        21.673110735169658
                    ],
                    [
                        2.0987158568620603,
                        -16.0
                    ],
                    [
                        -11.666666666666666,
                        -13.333333333333332
                    ],
                    [
                        -25.432049190195393,
                        -14.80002039628525
                    ]
                ]
            },
            "Rhood": {
                "translation": [
                    -8.666666666666666,
                    53.33333333333333,
                    -6.666666666666666
                ],
                "edges": [
                    {
                        "endpoints": [
                            4,
                            3
                        ]
                    },
                    {
                        "endpoints": [
                            3,
                            2
                        ],
                        "curvature": [
                            0.3,
                            -0.6
                        ]
                    },
                    {
                        "endpoints": [
                            2,
                            1
                        ]
                    },
                    {
                        "endpoints": [
                            1,
                            0
                        ]
                    },
                    {
                        "endpoints": [
                            0,
                            4
                        ]
                    }
                ],
                "rotation": [
                    0.0,
                    90,
                    180.0
                ],
                "vertices": [
                    [
                        -25.432049190195393,
                        14.80002039628525
                    ],
                    [
                        -11.666666666666666,
                        13.333333333333332
                    ],
                    [
                        2.0987158568620603,
                        16.0
                    ],
                    [
                        -5.688060483173091,
                        -21.673110735169658
                    ],
                    [
                        -23.333333333333332,
                        -24.756423684317213
                    ]
                ]
            }
        },
        "stitches": [
            [
                {
                    "edge": 3,
                    "panel": "back"
                },
                {
                    "edge": 3,
                    "panel": "front_right"
                }
            ],
            [
                {
                    "edge": 1,
                    "panel": "back"
                },
                {
                    "edge": 5,
                    "panel": "front_right"
                }
            ],
            [
                {
                    "edge": 8,
                    "panel": "back"
                },
                {
                    "edge": 1,
                    "panel": "front_left"
                }
            ],
            [
                {
                    "edge": 6,
                    "panel": "back"
                },
                {
                    "edge": 3,
                    "panel": "front_left"
                }
            ],
            [
                {
                    "edge": 0,
                    "panel": "Rhood"
                },
                {
                    "edge": 3,
                    "panel": "Lhood"
                }
            ],
            [
                {
                    "edge": 1,
                    "panel": "Rhood"
                },
                {
                    "edge": 2,
                    "panel": "Lhood"
                }
            ],
            [
                {
                    "edge": 3,
                    "panel": "Rhood"
                },
                {
                    "edge": 2,
                    "panel": "front_right"
                }
            ],
            [
                {
                    "edge": 0,
                    "panel": "Lhood"
                },
                {
                    "edge": 4,
                    "panel": "front_left"
                }
            ],
            [
                {
                    "edge": 2,
                    "panel": "Rhood"
                },
                {
                    "edge": 4,
                    "panel": "back"
                }
            ],
            [
                {
                    "edge": 1,
                    "panel": "Lhood"
                },
                {
                    "edge": 5,
                    "panel": "back"
                }
            ]
        ],
        "panel_order": [
            "front_right",
            "Rhood",
            "back",
            "Lhood",
            "front_left"
        ]
    },
    "properties": {
        "curvature_coords": "relative",
        "normalize_panel_translation": false,
        "units_in_meter": 100,
        "normalized_edge_loops": true
    },
    "parameters": {
        "low_wide": {
            "influence": [
                {
                    "edge_list": [
                        {
                            "direction": "both",
                            "id": 0
                        }
                    ],
                    "panel": "back"
                },
                {
                    "edge_list": [
                        {
                            "direction": "end",
                            "id": 0
                        }
                    ],
                    "panel": "front_left"
                },
                {
                    "edge_list": [
                        {
                            "direction": "start",
                            "id": 0
                        }
                    ],
                    "panel": "front_right"
                }
            ],
            "range": [
                0.7,
                2.5
            ],
            "type": "length",
            "value": 1.6907043280811367
        },
        "length": {
            "influence": [
                {
                    "edge_list": [
                        {
                            "direction": "end",
                            "id": [
                                5,
                                0
                            ],
                            "along": [
                                0,
                                1
                            ]
                        }
                    ],
                    "panel": "front_right"
                },
                {
                    "edge_list": [
                        {
                            "direction": "start",
                            "id": [
                                0,
                                1
                            ],
                            "along": [
                                0,
                                1
                            ]
                        }
                    ],
                    "panel": "front_left"
                },
                {
                    "edge_list": [
                        {
                            "direction": "start",
                            "id": 1,
                            "along": [
                                0,
                                1
                            ]
                        },
                        {
                            "direction": "end",
                            "id": 8,
                            "along": [
                                0,
                                1
                            ]
                        }
                    ],
                    "panel": "back"
                }
            ],
            "range": [
                0.3,
                2.7
            ],
            "type": "length",
            "value": 1.6197100540067133
        },
        "collar_wide": {
            "influence": [
                {
                    "edge_list": [
                        {
                            "direction": "end",
                            "id": [
                                2
                            ],
                            "along": [
                                1,
                                0
                            ]
                        }
                    ],
                    "panel": "front_right"
                },
                {
                    "edge_list": [
                        {
                            "direction": "start",
                            "id": [
                                4
                            ],
                            "along": [
                                1,
                                0
                            ]
                        }
                    ],
                    "panel": "front_left"
                },
                {
                    "edge_list": [
                        {
                            "direction": "both",
                            "id": [
                                4,
                                5
                            ],
                            "along": [
                                1,
                                0
                            ]
                        }
                    ],
                    "panel": "back"
                },
                {
                    "edge_list": [
                        {
                            "direction": "start",
                            "along": [
                                1,
                                0
                            ],
                            "id": 0
                        },
                        {
                            "direction": "end",
                            "along": [
                                1,
                                0
                            ],
                            "id": 1
                        }
                    ],
                    "panel": "Lhood"
                },
                {
                    "edge_list": [
                        {
                            "direction": "end",
                            "along": [
                                1,
                                0
                            ],
                            "id": 3
                        },
                        {
                            "direction": "start",
                            "along": [
                                1,
                                0
                            ],
                            "id": 2
                        }
                    ],
                    "panel": "Rhood"
                }
            ],
            "range": [
                0.5,
                1.5
            ],
            "type": "length",
            "value": 1.1619230869733912
        },
        "wideness": {
            "influence": [
                {
                    "edge_list": [
                        {
                            "direction": "end",
                            "id": [
                                2,
                                3,
                                4
                            ],
                            "along": [
                                1,
                                0
                            ]
                        },
                        {
                            "direction": "start",
                            "id": 0,
                            "along": [
                                1,
                                0
                            ]
                        }
                    ],
                    "panel": "front_right"
                },
                {
                    "edge_list": [
                        {
                            "direction": "start",
                            "id": [
                                2,
                                3,
                                4
                            ],
                            "along": [
                                1,
                                0
                            ]
                        },
                        {
                            "direction": "end",
                            "id": 0,
                            "along": [
                                1,
                                0
                            ]
                        }
                    ],
                    "panel": "front_left"
                },
                {
                    "edge_list": [
                        {
                            "direction": "both",
                            "id": [
                                2,
                                3,
                                5,
                                6,
                                7
                            ]
                        },
                        {
                            "direction": "both",
                            "id": 0
                        }
                    ],
                    "panel": "back"
                },
                {
                    "edge_list": [
                        {
                            "direction": "start",
                            "along": [
                                1,
                                0
                            ],
                            "id": 0
                        },
                        {
                            "direction": "end",
                            "along": [
                                1,
                                0
                            ],
                            "id": 1
                        }
                    ],
                    "panel": "Lhood"
                },
                {
                    "edge_list": [
                        {
                            "direction": "end",
                            "along": [
                                1,
                                0
                            ],
                            "id": 3
                        },
                        {
                            "direction": "start",
                            "along": [
                                1,
                                0
                            ],
                            "id": 2
                        }
                    ],
                    "panel": "Rhood"
                }
            ],
            "range": [
                0.9,
                1.5
            ],
            "type": "length",
            "value": 1.4216482324369855
        },
        "fcollar_depth": {
            "influence": [
                {
                    "edge_list": [
                        {
                            "direction": "start",
                            "along": [
                                0,
                                1
                            ],
                            "id": 2
                        }
                    ],
                    "panel": "front_right"
                },
                {
                    "edge_list": [
                        {
                            "direction": "end",
                            "along": [
                                0,
                                1
                            ],
                            "id": 4
                        }
                    ],
                    "panel": "front_left"
                },
                {
                    "edge_list": [
                        {
                            "direction": "start",
                            "along": [
                                0,
                                1
                            ],
                            "id": 0
                        }
                    ],
                    "panel": "Lhood"
                },
                {
                    "edge_list": [
                        {
                            "direction": "end",
                            "along": [
                                0,
                                1
                            ],
                            "id": 3
                        }
                    ],
                    "panel": "Rhood"
                }
            ],
            "range": [
                0.1,
                1.7
            ],
            "type": "length",
            "value": 0.12571603396730727
        },
        "sldepth": {
            "influence": [
                {
                    "edge_list": [
                        {
                            "direction": "end",
                            "along": [
                                0,
                                1
                            ],
                            "id": 4
                        }
                    ],
                    "panel": "front_right"
                },
                {
                    "edge_list": [
                        {
                            "direction": "start",
                            "along": [
                                0,
                                1
                            ],
                            "id": 2
                        }
                    ],
                    "panel": "front_left"
                },
                {
                    "edge_list": [
                        {
                            "direction": "end",
                            "along": [
                                0,
                                1
                            ],
                            "id": 7
                        },
                        {
                            "direction": "start",
                            "along": [
                                0,
                                1
                            ],
                            "id": 2
                        }
                    ],
                    "panel": "back"
                }
            ],
            "range": [
                0.85,
                2.5
            ],
            "type": "length",
            "value": 1.7912861900775408
        },
        "hood_height": {
            "influence": [
                {
                    "edge_list": [
                        {
                            "along": [
                                0,
                                1
                            ],
                            "direction": "end",
                            "id": 2
                        },
                        {
                            "along": [
                                0,
                                1
                            ],
                            "direction": "start",
                            "id": 4
                        }
                    ],
                    "panel": "Lhood"
                },
                {
                    "edge_list": [
                        {
                            "along": [
                                0,
                                1
                            ],
                            "direction": "end",
                            "id": 4
                        },
                        {
                            "along": [
                                0,
                                1
                            ],
                            "direction": "start",
                            "id": 1
                        }
                    ],
                    "panel": "Rhood"
                }
            ],
            "range": [
                0.85,
                1.2
            ],
            "type": "length",
            "value": 1.1941541684236132
        },
        "hood_depth": {
            "influence": [
                {
                    "edge_list": [
                        {
                            "direction": "start",
                            "id": 3
                        }
                    ],
                    "panel": "Lhood"
                },
                {
                    "edge_list": [
                        {
                            "direction": "end",
                            "id": 0
                        }
                    ],
                    "panel": "Rhood"
                }
            ],
            "range": [
                0.3,
                2.5
            ],
            "type": "length",
            "value": 1.7645272850160243
        }
    },
    "parameter_order": [
        "hood_height",
        "hood_depth",
        "collar_wide",
        "fcollar_depth",
        "wideness",
        "length",
        "low_wide",
        "sldepth"
    ],
    "global_translation": {
        "height": [
            0,
            119.8429946899414,
            0
        ],
        "front": [
            0,
            0,
            0.3929004669189453
        ],
        "back": [
            0,
            0,
            -0.45979976654052734
        ]
    }
}