{
    "pattern": {
        "panels": {
            "back": {
                "translation": [
                    -0.17666666666666703,
                    9.85,
                    -15.51
                ],
                "edges": [
                    {
                        "endpoints": [
                            4,
                            3
                        ]
                    },
                    {
                        "endpoints": [
                            3,
                            2
                        ]
                    },
                    {
                        "endpoints": [
                            2,
                            1
                        ],
                        "curvature": [
                            0.3,
                            0.4
                        ]
                    },
                    {
                        "endpoints": [
                            1,
                            0
                        ]
                    },
                    {
                        "endpoints": [
                            0,
                            7
                        ],
                        "curvature": [
                            0.5,
                            1.1295628172728227
                        ]
                    },
                    {
                        "endpoints": [
                            7,
                            6
                        ]
                    },
                    {
                        "endpoints": [
                            6,
                            5
                        ],
                        "curvature": [
                            0.7,
                            0.4
                        ]
                    },
                    {
                        "endpoints": [
                            5,
                            4
                        ]
                    }
                ],
                "rotation": [
                    180.0,
                    -0.0,
                    180.0
                ],
                "vertices": [
                    [
                        9.280493813170475,
                        19.583333333333332
                    ],
                    [
                        26.932354261845468,
                        19.583333333333332
                    ],
                    [
                        31.829145945817366,
                        -12.287992195935631
                    ],
                    [
                        77.65295306306137,
                        -41.90288272758588
                    ],
                    [
                        -77.65295306306137,
                        -41.90288272758588
                    ],
                    [
                        -31.829145945817366,
                        -12.287992195935631
                    ],
                    [
                        -26.932354261845468,
                        19.583333333333332
                    ],
                    [
                        -9.280493813170475,
                        19.583333333333332
                    ]
                ]
            },
            "front_right": {
                "translation": [
                    0.17666666666666703,
                    10.743979826009564,
                    18.759999999999998
                ],
                "edges": [
                    {
                        "endpoints": [
                            4,
                            5
                        ]
                    },
                    {
                        "endpoints": [
                            5,
                            0
                        ]
                    },
                    {
                        "endpoints": [
                            0,
                            1
                        ]
                    },
                    {
                        "endpoints": [
                            1,
                            2
                        ]
                    },
                    {
                        "endpoints": [
                            2,
                            3
                        ],
                        "curvature": [
                            0.7,
                            0.4
                        ]
                    },
                    {
                        "endpoints": [
                            3,
                            4
                        ]
                    }
                ],
                "rotation": [
                    0.0,
                    0.0,
                    0.0
                ],
                "vertices": [
                    [
                        0.0,
                        8.99396904454825
                    ],
                    [
                        -9.280493813170475,
                        18.703703703703702
                    ],
                    [
                        -26.932354261845468,
                        18.703703703703702
                    ],
                    [
                        -31.829145945817366,
                        -13.167621825565252
                    ],
                    [
                        -77.65295306306137,
                        -42.782512357215516
                    ],
                    [
                        0.0,
                        -42.782512357215516
                    ]
                ]
            },
            "front_left": {
                "translation": [
                    0.17666666666666703,
                    10.743979826009564,
                    18.759999999999998
                ],
                "edges": [
                    {
                        "endpoints": [
                            1,
                            2
                        ]
                    },
                    {
                        "endpoints": [
                            2,
                            3
                        ]
                    },
                    {
                        "endpoints": [
                            3,
                            4
                        ],
                        "curvature": [
                            0.3,
                            0.4
                        ]
                    },
                    {
                        "endpoints": [
                            4,
                            5
                        ]
                    },
                    {
                        "endpoints": [
                            5,
                            0
                        ]
                    },
                    {
                        "endpoints": [
                            0,
                            1
                        ]
                    }
                ],
                "rotation": [
                    0.0,
                    0.0,
                    0.0
                ],
                "vertices": [
                    [
                        0.0,
                        8.99396904454825
                    ],
                    [
                        0.0,
                        -42.782512357215516
                    ],
                    [
                        77.65295306306137,
                        -42.782512357215516
                    ],
                    [
                        31.829145945817366,
                        -13.167621825565252
                    ],
                    [
                        26.932354261845468,
                        18.703703703703702
                    ],
                    [
                        9.280493813170475,
                        18.703703703703702
                    ]
                ]
            }
        },
        "stitches": [
            [
                {
                    "edge": 3,
                    "panel": "back"
                },
                {
                    "edge": 3,
                    "panel": "front_right"
                }
            ],
            [
                {
                    "edge": 1,
                    "panel": "back"
                },
                {
                    "edge": 5,
                    "panel": "front_right"
                }
            ],
            [
                {
                    "edge": 7,
                    "panel": "back"
                },
                {
                    "edge": 1,
                    "panel": "front_left"
                }
            ],
            [
                {
                    "edge": 5,
                    "panel": "back"
                },
                {
                    "edge": 3,
                    "panel": "front_left"
                }
            ]
        ],
        "panel_order": [
            "front_right",
            "back",
            "front_left"
        ]
    },
    "properties": {
        "curvature_coords": "relative",
        "normalize_panel_translation": false,
        "units_in_meter": 100,
        "normalized_edge_loops": true
    },
    "parameters": {
        "low_wide": {
            "influence": [
                {
                    "edge_list": [
                        {
                            "direction": "both",
                            "id": 0
                        }
                    ],
                    "panel": "back"
                },
                {
                    "edge_list": [
                        {
                            "direction": "end",
                            "id": 0
                        }
                    ],
                    "panel": "front_left"
                },
                {
                    "edge_list": [
                        {
                            "direction": "start",
                            "id": 0
                        }
                    ],
                    "panel": "front_right"
                }
            ],
            "range": [
                0.7,
                2.5
            ],
            "type": "length",
            "value": 2.439680700049247
        },
        "length": {
            "influence": [
                {
                    "edge_list": [
                        {
                            "direction": "end",
                            "id": [
                                5,
                                0
                            ],
                            "along": [
                                0,
                                1
                            ]
                        }
                    ],
                    "panel": "front_right"
                },
                {
                    "edge_list": [
                        {
                            "direction": "start",
                            "id": [
                                0,
                                1
                            ],
                            "along": [
                                0,
                                1
                            ]
                        }
                    ],
                    "panel": "front_left"
                },
                {
                    "edge_list": [
                        {
                            "direction": "start",
                            "id": 1,
                            "along": [
                                0,
                                1
                            ]
                        },
                        {
                            "direction": "end",
                            "id": 7,
                            "along": [
                                0,
                                1
                            ]
                        }
                    ],
                    "panel": "back"
                }
            ],
            "range": [
                0.3,
                2.7
            ],
            "type": "length",
            "value": 0.9959899865389457
        },
        "collar_wide": {
            "influence": [
                {
                    "edge_list": [
                        {
                            "direction": "end",
                            "id": [
                                2
                            ],
                            "along": [
                                1,
                                0
                            ]
                        }
                    ],
                    "panel": "front_right"
                },
                {
                    "edge_list": [
                        {
                            "direction": "start",
                            "id": [
                                4
                            ],
                            "along": [
                                1,
                                0
                            ]
                        }
                    ],
                    "panel": "front_left"
                },
                {
                    "edge_list": [
                        {
                            "direction": "both",
                            "id": 4
                        }
                    ],
                    "panel": "back"
                }
            ],
            "range": [
                0.5,
                1.5
            ],
            "type": "length",
            "value": 0.7580876959538416
        },
        "bcollar_depth": {
            "influence": [
                {
                    "edge_list": [
                        4
                    ],
                    "panel": "back"
                }
            ],
            "range": [
                0.1,
                12
            ],
            "type": "curve",
            "value": 3.7652093909094093
        },
        "wideness": {
            "influence": [
                {
                    "edge_list": [
                        {
                            "direction": "end",
                            "id": [
                                2,
                                3,
                                4
                            ],
                            "along": [
                                1,
                                0
                            ]
                        },
                        {
                            "direction": "start",
                            "id": 0,
                            "along": [
                                1,
                                0
                            ]
                        }
                    ],
                    "panel": "front_right"
                },
                {
                    "edge_list": [
                        {
                            "direction": "start",
                            "id": [
                                2,
                                3,
                                4
                            ],
                            "along": [
                                1,
                                0
                            ]
                        },
                        {
                            "direction": "end",
                            "id": 0,
                            "along": [
                                1,
                                0
                            ]
                        }
                    ],
                    "panel": "front_left"
                },
                {
                    "edge_list": [
                        {
                            "direction": "both",
                            "id": [
                                2,
                                3,
                                4,
                                5,
                                6
                            ]
                        },
                        {
                            "direction": "both",
                            "id": 0
                        }
                    ],
                    "panel": "back"
                }
            ],
            "range": [
                0.9,
                1.5
            ],
            "type": "length",
            "value": 1.469037505191571
        },
        "fcollar_depth": {
            "influence": [
                {
                    "edge_list": [
                        {
                            "direction": "start",
                            "along": [
                                0,
                                1
                            ],
                            "id": 2
                        }
                    ],
                    "panel": "front_right"
                },
                {
                    "edge_list": [
                        {
                            "direction": "end",
                            "along": [
                                0,
                                1
                            ],
                            "id": 4
                        }
                    ],
                    "panel": "front_left"
                }
            ],
            "range": [
                0.1,
                3
            ],
            "type": "length",
            "value": 0.8322629707847535
        },
        "sldepth": {
            "influence": [
                {
                    "edge_list": [
                        {
                            "direction": "end",
                            "along": [
                                0,
                                1
                            ],
                            "id": 4
                        }
                    ],
                    "panel": "front_right"
                },
                {
                    "edge_list": [
                        {
                            "direction": "start",
                            "along": [
                                0,
                                1
                            ],
                            "id": 2
                        }
                    ],
                    "panel": "front_left"
                },
                {
                    "edge_list": [
                        {
                            "direction": "end",
                            "along": [
                                0,
                                1
                            ],
                            "id": 6
                        },
                        {
                            "direction": "start",
                            "along": [
                                0,
                                1
                            ],
                            "id": 2
                        }
                    ],
                    "panel": "back"
                }
            ],
            "range": [
                0.85,
                2.5
            ],
            "type": "length",
            "value": 1.912279531756138
        }
    },
    "parameter_order": [
        "collar_wide",
        "fcollar_depth",
        "bcollar_depth",
        "wideness",
        "length",
        "low_wide",
        "sldepth"
    ],
    "global_translation": {
        "height": [
            0,
            110.96349334716797,
            0
        ],
        "front": [
            0,
            0,
            1.2201004028320312
        ],
        "back": [
            0,
            0,
            -0.3625001907348633
        ]
    }
}