{
    "pattern": {
        "panels": {
            "back": {
                "translation": [
                    -0.17666666666666703,
                    9.85,
                    -14.176666666666666
                ],
                "edges": [
                    {
                        "endpoints": [
                            4,
                            3
                        ]
                    },
                    {
                        "endpoints": [
                            3,
                            2
                        ]
                    },
                    {
                        "endpoints": [
                            2,
                            1
                        ],
                        "curvature": [
                            0.3,
                            0.4
                        ]
                    },
                    {
                        "endpoints": [
                            1,
                            0
                        ]
                    },
                    {
                        "endpoints": [
                            0,
                            8
                        ]
                    },
                    {
                        "endpoints": [
                            8,
                            7
                        ]
                    },
                    {
                        "endpoints": [
                            7,
                            6
                        ]
                    },
                    {
                        "endpoints": [
                            6,
                            5
                        ],
                        "curvature": [
                            0.7,
                            0.4
                        ]
                    },
                    {
                        "endpoints": [
                            5,
                            4
                        ]
                    }
                ],
                "rotation": [
                    180.0,
                    -0.0,
                    180.0
                ],
                "vertices": [
                    [
                        16.913597765095844,
                        19.583333333333332
                    ],
                    [
                        26.83826392434363,
                        19.583333333333332
                    ],
                    [
                        31.71794827422429,
                        -5.438583295893842
                    ],
                    [
                        29.71775038332391,
                        -103.0020740550305
                    ],
                    [
                        -29.71775038332391,
                        -103.0020740550305
                    ],
                    [
                        -31.71794827422429,
                        -5.438583295893842
                    ],
                    [
                        -26.83826392434363,
                        19.583333333333332
                    ],
                    [
                        -16.913597765095844,
                        19.583333333333332
                    ],
                    [
                        0.0,
                        16.916666666666664
                    ]
                ]
            },
            "front_right": {
                "translation": [
                    -5.176666666666667,
                    10.743979826009564,
                    15.426666666666666
                ],
                "edges": [
                    {
                        "endpoints": [
                            4,
                            5
                        ]
                    },
                    {
                        "endpoints": [
                            5,
                            0
                        ]
                    },
                    {
                        "endpoints": [
                            0,
                            1
                        ]
                    },
                    {
                        "endpoints": [
                            1,
                            2
                        ]
                    },
                    {
                        "endpoints": [
                            2,
                            3
                        ],
                        "curvature": [
                            0.7,
                            0.4
                        ]
                    },
                    {
                        "endpoints": [
                            3,
                            4
                        ]
                    }
                ],
                "rotation": [
                    0.0,
                    0.0,
                    0.0
                ],
                "vertices": [
                    [
                        0.0,
                        5.062838449799802
                    ],
                    [
                        -16.913597765095844,
                        18.703703703703702
                    ],
                    [
                        -26.83826392434363,
                        18.703703703703702
                    ],
                    [
                        -31.71794827422429,
                        -6.318212925523466
                    ],
                    [
                        -29.71775038332391,
                        -103.88170368466015
                    ],
                    [
                        0.0,
                        -103.88170368466015
                    ]
                ]
            },
            "front_left": {
                "translation": [
                    5.176666666666667,
                    10.743979826009564,
                    15.426666666666666
                ],
                "edges": [
                    {
                        "endpoints": [
                            1,
                            2
                        ]
                    },
                    {
                        "endpoints": [
                            2,
                            3
                        ]
                    },
                    {
                        "endpoints": [
                            3,
                            4
                        ],
                        "curvature": [
                            0.3,
                            0.4
                        ]
                    },
                    {
                        "endpoints": [
                            4,
                            5
                        ]
                    },
                    {
                        "endpoints": [
                            5,
                            0
                        ]
                    },
                    {
                        "endpoints": [
                            0,
                            1
                        ]
                    }
                ],
                "rotation": [
                    0.0,
                    0.0,
                    0.0
                ],
                "vertices": [
                    [
                        0.0,
                        5.062838449799802
                    ],
                    [
                        0.0,
                        -103.88170368466015
                    ],
                    [
                        29.71775038332391,
                        -103.88170368466015
                    ],
                    [
                        31.71794827422429,
                        -6.318212925523466
                    ],
                    [
                        26.83826392434363,
                        18.703703703703702
                    ],
                    [
                        16.913597765095844,
                        18.703703703703702
                    ]
                ]
            },
            "Lhood": {
                "translation": [
                    8.666666666666666,
                    53.33333333333333,
                    -6.666666666666666
                ],
                "edges": [
                    {
                        "endpoints": [
                            4,
                            3
                        ]
                    },
                    {
                        "endpoints": [
                            3,
                            2
                        ]
                    },
                    {
                        "endpoints": [
                            2,
                            1
                        ],
                        "curvature": [
                            0.7,
                            -0.6
                        ]
                    },
                    {
                        "endpoints": [
                            1,
                            0
                        ]
                    },
                    {
                        "endpoints": [
                            0,
                            4
                        ]
                    }
                ],
                "rotation": [
                    0.0,
                    90.0,
                    0.0
                ],
                "vertices": [
                    [
                        -23.333333333333332,
                        23.333923424272893
                    ],
                    [
                        -4.384657121729031,
                        20.60507253065145
                    ],
                    [
                        5.246931098429187,
                        -16.0
                    ],
                    [
                        -11.666666666666666,
                        -13.333333333333332
                    ],
                    [
                        -28.58026443176252,
                        -26.97419858723724
                    ]
                ]
            },
            "Rhood": {
                "translation": [
                    -8.666666666666666,
                    53.33333333333333,
                    -6.666666666666666
                ],
                "edges": [
                    {
                        "endpoints": [
                            4,
                            3
                        ]
                    },
                    {
                        "endpoints": [
                            3,
                            2
                        ],
                        "curvature": [
                            0.3,
                            -0.6
                        ]
                    },
                    {
                        "endpoints": [
                            2,
                            1
                        ]
                    },
                    {
                        "endpoints": [
                            1,
                            0
                        ]
                    },
                    {
                        "endpoints": [
                            0,
                            4
                        ]
                    }
                ],
                "rotation": [
                    0.0,
                    90,
                    180.0
                ],
                "vertices": [
                    [
                        -28.58026443176252,
                        26.97419858723724
                    ],
                    [
                        -11.666666666666666,
                        13.333333333333332
                    ],
                    [
                        5.246931098429187,
                        16.0
                    ],
                    [
                        -4.384657121729031,
                        -20.60507253065145
                    ],
                    [
                        -23.333333333333332,
                        -23.333923424272893
                    ]
                ]
            }
        },
        "stitches": [
            [
                {
                    "edge": 3,
                    "panel": "back"
                },
                {
                    "edge": 3,
                    "panel": "front_right"
                }
            ],
            [
                {
                    "edge": 1,
                    "panel": "back"
                },
                {
                    "edge": 5,
                    "panel": "front_right"
                }
            ],
            [
                {
                    "edge": 8,
                    "panel": "back"
                },
                {
                    "edge": 1,
                    "panel": "front_left"
                }
            ],
            [
                {
                    "edge": 6,
                    "panel": "back"
                },
                {
                    "edge": 3,
                    "panel": "front_left"
                }
            ],
            [
                {
                    "edge": 0,
                    "panel": "Rhood"
                },
                {
                    "edge": 3,
                    "panel": "Lhood"
                }
            ],
            [
                {
                    "edge": 1,
                    "panel": "Rhood"
                },
                {
                    "edge": 2,
                    "panel": "Lhood"
                }
            ],
            [
                {
                    "edge": 3,
                    "panel": "Rhood"
                },
                {
                    "edge": 2,
                    "panel": "front_right"
                }
            ],
            [
                {
                    "edge": 0,
                    "panel": "Lhood"
                },
                {
                    "edge": 4,
                    "panel": "front_left"
                }
            ],
            [
                {
                    "edge": 2,
                    "panel": "Rhood"
                },
                {
                    "edge": 4,
                    "panel": "back"
                }
            ],
            [
                {
                    "edge": 1,
                    "panel": "Lhood"
                },
                {
                    "edge": 5,
                    "panel": "back"
                }
            ]
        ],
        "panel_order": [
            "front_right",
            "Rhood",
            "back",
            "Lhood",
            "front_left"
        ]
    },
    "properties": {
        "curvature_coords": "relative",
        "normalize_panel_translation": false,
        "units_in_meter": 100,
        "normalized_edge_loops": true
    },
    "parameters": {
        "low_wide": {
            "influence": [
                {
                    "edge_list": [
                        {
                            "direction": "both",
                            "id": 0
                        }
                    ],
                    "panel": "back"
                },
                {
                    "edge_list": [
                        {
                            "direction": "end",
                            "id": 0
                        }
                    ],
                    "panel": "front_left"
                },
                {
                    "edge_list": [
                        {
                            "direction": "start",
                            "id": 0
                        }
                    ],
                    "panel": "front_right"
                }
            ],
            "range": [
                0.7,
                2.5
            ],
            "type": "length",
            "value": 0.9369379799220541
        },
        "length": {
            "influence": [
                {
                    "edge_list": [
                        {
                            "direction": "end",
                            "id": [
                                5,
                                0
                            ],
                            "along": [
                                0,
                                1
                            ]
                        }
                    ],
                    "panel": "front_right"
                },
                {
                    "edge_list": [
                        {
                            "direction": "start",
                            "id": [
                                0,
                                1
                            ],
                            "along": [
                                0,
                                1
                            ]
                        }
                    ],
                    "panel": "front_left"
                },
                {
                    "edge_list": [
                        {
                            "direction": "start",
                            "id": 1,
                            "along": [
                                0,
                                1
                            ]
                        },
                        {
                            "direction": "end",
                            "id": 8,
                            "along": [
                                0,
                                1
                            ]
                        }
                    ],
                    "panel": "back"
                }
            ],
            "range": [
                0.3,
                2.7
            ],
            "type": "length",
            "value": 2.353749793815493
        },
        "collar_wide": {
            "influence": [
                {
                    "edge_list": [
                        {
                            "direction": "end",
                            "id": [
                                2
                            ],
                            "along": [
                                1,
                                0
                            ]
                        }
                    ],
                    "panel": "front_right"
                },
                {
                    "edge_list": [
                        {
                            "direction": "start",
                            "id": [
                                4
                            ],
                            "along": [
                                1,
                                0
                            ]
                        }
                    ],
                    "panel": "front_left"
                },
                {
                    "edge_list": [
                        {
                            "direction": "both",
                            "id": [
                                4,
                                5
                            ],
                            "along": [
                                1,
                                0
                            ]
                        }
                    ],
                    "panel": "back"
                },
                {
                    "edge_list": [
                        {
                            "direction": "start",
                            "along": [
                                1,
                                0
                            ],
                            "id": 0
                        },
                        {
                            "direction": "end",
                            "along": [
                                1,
                                0
                            ],
                            "id": 1
                        }
                    ],
                    "panel": "Lhood"
                },
                {
                    "edge_list": [
                        {
                            "direction": "end",
                            "along": [
                                1,
                                0
                            ],
                            "id": 3
                        },
                        {
                            "direction": "start",
                            "along": [
                                1,
                                0
                            ],
                            "id": 2
                        }
                    ],
                    "panel": "Rhood"
                }
            ],
            "range": [
                0.5,
                1.5
            ],
            "type": "length",
            "value": 1.3864501514742034
        },
        "wideness": {
            "influence": [
                {
                    "edge_list": [
                        {
                            "direction": "end",
                            "id": [
                                2,
                                3,
                                4
                            ],
                            "along": [
                                1,
                                0
                            ]
                        },
                        {
                            "direction": "start",
                            "id": 0,
                            "along": [
                                1,
                                0
                            ]
                        }
                    ],
                    "panel": "front_right"
                },
                {
                    "edge_list": [
                        {
                            "direction": "start",
                            "id": [
                                2,
                                3,
                                4
                            ],
                            "along": [
                                1,
                                0
                            ]
                        },
                        {
                            "direction": "end",
                            "id": 0,
                            "along": [
                                1,
                                0
                            ]
                        }
                    ],
                    "panel": "front_left"
                },
                {
                    "edge_list": [
                        {
                            "direction": "both",
                            "id": [
                                2,
                                3,
                                5,
                                6,
                                7
                            ]
                        },
                        {
                            "direction": "both",
                            "id": 0
                        }
                    ],
                    "panel": "back"
                },
                {
                    "edge_list": [
                        {
                            "direction": "start",
                            "along": [
                                1,
                                0
                            ],
                            "id": 0
                        },
                        {
                            "direction": "end",
                            "along": [
                                1,
                                0
                            ],
                            "id": 1
                        }
                    ],
                    "panel": "Lhood"
                },
                {
                    "edge_list": [
                        {
                            "direction": "end",
                            "along": [
                                1,
                                0
                            ],
                            "id": 3
                        },
                        {
                            "direction": "start",
                            "along": [
                                1,
                                0
                            ],
                            "id": 2
                        }
                    ],
                    "panel": "Rhood"
                }
            ],
            "range": [
                0.9,
                1.5
            ],
            "type": "length",
            "value": 1.4639053049641981
        },
        "fcollar_depth": {
            "influence": [
                {
                    "edge_list": [
                        {
                            "direction": "start",
                            "along": [
                                0,
                                1
                            ],
                            "id": 2
                        }
                    ],
                    "panel": "front_right"
                },
                {
                    "edge_list": [
                        {
                            "direction": "end",
                            "along": [
                                0,
                                1
                            ],
                            "id": 4
                        }
                    ],
                    "panel": "front_left"
                },
                {
                    "edge_list": [
                        {
                            "direction": "start",
                            "along": [
                                0,
                                1
                            ],
                            "id": 0
                        }
                    ],
                    "panel": "Lhood"
                },
                {
                    "edge_list": [
                        {
                            "direction": "end",
                            "along": [
                                0,
                                1
                            ],
                            "id": 3
                        }
                    ],
                    "panel": "Rhood"
                }
            ],
            "range": [
                0.1,
                1.7
            ],
            "type": "length",
            "value": 1.169217021763192
        },
        "sldepth": {
            "influence": [
                {
                    "edge_list": [
                        {
                            "direction": "end",
                            "along": [
                                0,
                                1
                            ],
                            "id": 4
                        }
                    ],
                    "panel": "front_right"
                },
                {
                    "edge_list": [
                        {
                            "direction": "start",
                            "along": [
                                0,
                                1
                            ],
                            "id": 2
                        }
                    ],
                    "panel": "front_left"
                },
                {
                    "edge_list": [
                        {
                            "direction": "end",
                            "along": [
                                0,
                                1
                            ],
                            "id": 7
                        },
                        {
                            "direction": "start",
                            "along": [
                                0,
                                1
                            ],
                            "id": 2
                        }
                    ],
                    "panel": "back"
                }
            ],
            "range": [
                0.85,
                2.5
            ],
            "type": "length",
            "value": 1.5013149977536306
        },
        "hood_height": {
            "influence": [
                {
                    "edge_list": [
                        {
                            "along": [
                                0,
                                1
                            ],
                            "direction": "end",
                            "id": 2
                        },
                        {
                            "along": [
                                0,
                                1
                            ],
                            "direction": "start",
                            "id": 4
                        }
                    ],
                    "panel": "Lhood"
                },
                {
                    "edge_list": [
                        {
                            "along": [
                                0,
                                1
                            ],
                            "direction": "end",
                            "id": 4
                        },
                        {
                            "along": [
                                0,
                                1
                            ],
                            "direction": "start",
                            "id": 1
                        }
                    ],
                    "panel": "Rhood"
                }
            ],
            "range": [
                0.85,
                1.2
            ],
            "type": "length",
            "value": 1.1600141621825495
        },
        "hood_depth": {
            "influence": [
                {
                    "edge_list": [
                        {
                            "direction": "start",
                            "id": 3
                        }
                    ],
                    "panel": "Lhood"
                },
                {
                    "edge_list": [
                        {
                            "direction": "end",
                            "id": 0
                        }
                    ],
                    "panel": "Rhood"
                }
            ],
            "range": [
                0.3,
                2.5
            ],
            "type": "length",
            "value": 1.8948676211604303
        }
    },
    "parameter_order": [
        "hood_height",
        "hood_depth",
        "collar_wide",
        "fcollar_depth",
        "wideness",
        "length",
        "low_wide",
        "sldepth"
    ],
    "global_translation": {
        "height": [
            0,
            126.57990264892578,
            0
        ],
        "front": [
            0,
            0,
            2.6401004791259766
        ],
        "back": [
            0,
            0,
            -1.723799705505371
        ]
    }
}